Metadata-Version: 1.1
Name: jasper-sys
Version: 0.2.1
Summary: JASPER SYS
Home-page: https://github.com/fabiocody/jasper.git
Author: Fabio Codiglioni
Author-email: fabiocody@icloud.com
License: MIT
Keywords: jasper,system,process monitor
Platform: UNKNOWN
Classifier: Programming Language :: Python :: 3.4
Classifier: Programming Language :: Python :: 3.5
Classifier: Programming Language :: Python :: 3.6
Classifier: Development Status :: 4 - Beta
